MANIFEST.in
README.rst
setup.py
pocker_ansible/VERSION
pocker_ansible/__init__.py
pocker_ansible/version.py
pocker_ansible.egg-info/PKG-INFO
pocker_ansible.egg-info/SOURCES.txt
pocker_ansible.egg-info/dependency_links.txt
pocker_ansible.egg-info/top_level.txt
pocker_ansible/filter_plugins/__init__.py
pocker_ansible/filter_plugins/pocker.py
pocker_ansible/library/__init__.py
pocker_ansible/library/pocker_cmd.py
pocker_ansible/library/pocker_cnt.py
pocker_ansible/library/pocker_dmn.py
pocker_ansible/library/pocker_img.py
pocker_ansible/library/pocker_net.py
pocker_ansible/library/pocker_vol.py