Metadata-Version: 1.1
Name: pocker-ansible
Version: 0.2.0
Summary: Collection of ansible plugins for docker orchestration using pocker library
Home-page: https://bitbucket.org/levelupdev/pocker-ansible
Author: Sergey Anuchin
Author-email: sergunich@gmail.com
License: MIT
Keywords: ansible docker pocker
Platform: UNKNOWN
Classifier: Development Status :: 4 - Beta
Classifier: Intended Audience :: Developers
Classifier: Intended Audience :: Information Technology
Classifier: License :: OSI Approved :: MIT License
Classifier: Natural Language :: English
Classifier: Operating System :: POSIX :: Linux
Classifier: Programming Language :: Python :: 2.6
Classifier: Programming Language :: Python :: 2.7
Classifier: Programming Language :: Python :: 2 :: Only 
Classifier: Topic :: System :: Systems Administration
Classifier: Topic :: Utilities
